itemadapter/__init__.py
itemadapter/adapter.py
itemadapter/utils.py
itemadapter-0.1.1.dist-info/LICENSE
itemadapter-0.1.1.dist-info/METADATA
itemadapter-0.1.1.dist-info/WHEEL
itemadapter-0.1.1.dist-info/top_level.txt
itemadapter-0.1.1.dist-info/RECORD
